README.md
README.rst
setup.py
Decision_Tree_Generator.egg-info/PKG-INFO
Decision_Tree_Generator.egg-info/SOURCES.txt
Decision_Tree_Generator.egg-info/dependency_links.txt
Decision_Tree_Generator.egg-info/top_level.txt
src/decision_tree/__init__.py
src/decision_tree/data_structures.py
src/decision_tree/extra.py
src/decision_tree/latex.py
src/decision_tree/tree_gen.py