Metadata-Version: 1.0
Name: Decision-Tree-Generator
Version: 0.0.3
Summary: Program for generating decision tree LaTeX code for array-based algorithms
Home-page: https://github.com/KYDronePilot/Decision-Tree-Generator
Author: KYDronePilot
Author-email: 33381603+KYDronePilot@users.noreply.github.com
License: GPL-3.0
Platform: UNKNOWN
